crossedwires/__init__.py
crossedwires/base_class.py
crossedwires/cifar10/__init__.py
crossedwires/cifar10/densenet121/__init__.py
crossedwires/cifar10/densenet121/densenet121_results.py
crossedwires/cifar10/resnet50/__init__.py
crossedwires/cifar10/resnet50/resnet50_results.py
crossedwires/cifar10/vgg16/__init__.py
crossedwires/cifar10/vgg16/vgg16_results.py
crossedwires-0.0.7.dist-info/LICENSE
crossedwires-0.0.7.dist-info/METADATA
crossedwires-0.0.7.dist-info/WHEEL
crossedwires-0.0.7.dist-info/top_level.txt
crossedwires-0.0.7.dist-info/RECORD
