Metadata-Version: 2.1
Name: crossedwires
Version: 0.0.7
Summary: CrossedWires: An Inter-framework ModelDivergence Dataset Generated using HyperparameterOptimization
Home-page: https://github.com/maxzvyagin/crossedwires
Author: Max Zvyagin
Author-email: mzvyagin@anl.gov
License: UNKNOWN
Keywords: pytorch,tensorflow,hpo,accuracy
Platform: UNKNOWN
Requires-Python: >=3.6
Requires-Dist: pytest
Requires-Dist: black
Requires-Dist: flake8
Requires-Dist: pre-commit
Requires-Dist: torch
Requires-Dist: torchvision
Requires-Dist: tensorflow
Requires-Dist: cross-framework-hpo
